[
    {
        "internal_id": 165461150,
        "Award ID": "75N97024F00001",
        "Recipient Name": "NEW TECH SOLUTIONS, INC.",
        "Start Date": "2023-12-14",
        "End Date": "2024-12-13",
        "Award Amount": 21618.4,
        "Description": "JFROG PRO X EDITION ARTIFACTORY",
        "Award Type": null,
        "generated_internal_id": "CONT_AWD_75N97024F00001_7529_HHSN316201500040W_7529"
    },
    {
        "internal_id": 165352980,
        "Award ID": "2033H624F00028",
        "Recipient Name": "FCN INC",
        "Start Date": "2023-11-03",
        "End Date": "2024-11-02",
        "Award Amount": 31500.0,
        "Description": "JFROG PRO X EDITION SOFTWARE LICENSES",
        "Award Type": null,
        "generated_internal_id": "CONT_AWD_2033H624F00028_2036_NNG15SC71B_8000"
    },
    {
        "internal_id": 163297280,
        "Award ID": "12314423F0767",
        "Recipient Name": "ADVANCED COMPUTER CONCEPTS, INC.",
        "Start Date": "2023-09-27",
        "End Date": "2024-09-27",
        "Award Amount": 43652.25,
        "Description": "JFROG ARTIFACTORY - JFROG X-RAY",
        "Award Type": null,
        "generated_internal_id": "CONT_AWD_12314423F0767_1205_NNG15SD60B_8000"
    },
    {
        "internal_id": 163300723,
        "Award ID": "2031JW23F00114",
        "Recipient Name": "BAHFED CORP",
        "Start Date": "2023-09-26",
        "End Date": "2024-09-25",
        "Award Amount": 121187.64,
        "Description": "JFROG ENTERPRISE+ SOFTWARE AND SUPPORT RENEWAL",
        "Award Type": null,
        "generated_internal_id": "CONT_AWD_2031JW23F00114_2046_NNG15SD09B_8000"
    },
    {
        "internal_id": 163117158,
        "Award ID": "693JJ623F00060N",
        "Recipient Name": "ENTERPRISE TECHNOLOGY SOLUTIONS, INC.",
        "Start Date": "2023-09-20",
        "End Date": "2024-09-20",
        "Award Amount": 21343.6,
        "Description": "THIS IS A FIRM-FIXED-PRICE NASA SEWP TASK ORDER: NNG15SD76B_693JJ623F00060N FOR JFROG PRO X EDITION SOFTWARE LICENSE THE FEDERAL RAILROAD ADMINISTRATION'S OFFICE OF INFORMATION TECHNOLOGY FOR A BASE AND ONE OPTION YEAR PERIODS.  BASE PERIOD OF",
        "Award Type": null,
        "generated_internal_id": "CONT_AWD_693JJ623F00060N_6930_NNG15SD76B_8000"
    },
    {
        "internal_id": 161714734,
        "Award ID": "12314423F0484",
        "Recipient Name": "ACCESSAGILITY LLC",
        "Start Date": "2023-09-18",
        "End Date": "2024-09-17",
        "Award Amount": 43987.2,
        "Description": "JFROG ARTIFACTORY ENTERPRISE SW RENEWAL",
        "Award Type": null,
        "generated_internal_id": "CONT_AWD_12314423F0484_1205_NNG15SC23B_8000"
    },
    {
        "internal_id": 161773797,
        "Award ID": "75N94023P00652",
        "Recipient Name": "GOVSMART, INC.",
        "Start Date": "2023-09-07",
        "End Date": "2024-09-06",
        "Award Amount": 58604.6,
        "Description": "BASE PACKAGE:JFROG ARTIFACTORY; JFROG XRAY; 30 PROJECT-BASED MANAGEMENT; AND 24/7 SLA SUPPORT12 MONTHS PLAN QTY4",
        "Award Type": null,
        "generated_internal_id": "CONT_AWD_75N94023P00652_7529_-NONE-_-NONE-"
    },
    {
        "internal_id": 162252370,
        "Award ID": "140F1G23F0100",
        "Recipient Name": "SOFTWARE INFORMATION RESOURCE CORP.",
        "Start Date": "2023-08-24",
        "End Date": "2024-08-29",
        "Award Amount": 21809.6,
        "Description": "VA-DBTS-ECOS JFROG ARTIFACTORY PRO-EDIT",
        "Award Type": null,
        "generated_internal_id": "CONT_AWD_140F1G23F0100_1448_NNG15SD74B_8000"
    },
    {
        "internal_id": 165890457,
        "Award ID": "N0017823FSA08",
        "Recipient Name": "BAHFED CORP",
        "Start Date": "2023-08-18",
        "End Date": "2024-08-17",
        "Award Amount": 44387.76,
        "Description": "P/N: JFROG-ENTERPRISE-X",
        "Award Type": null,
        "generated_internal_id": "CONT_AWD_N0017823FSA08_9700_NNG15SD09B_8000"
    },
    {
        "internal_id": 165463096,
        "Award ID": "N6600123F0922",
        "Recipient Name": "NEW TECH SOLUTIONS, INC.",
        "Start Date": "2023-08-03",
        "End Date": "2024-06-26",
        "Award Amount": 13390.44,
        "Description": "JFROG PRO EDITION",
        "Award Type": null,
        "generated_internal_id": "CONT_AWD_N6600123F0922_9700_NNG15SC82B_8000"
    },
    {
        "internal_id": 165431546,
        "Award ID": "N6600123F0928",
        "Recipient Name": "ADVANCED COMPUTER CONCEPTS, INC.",
        "Start Date": "2023-08-03",
        "End Date": "2024-08-29",
        "Award Amount": 25373.92,
        "Description": "JFROG PRO EDITION LICENSES SQ",
        "Award Type": null,
        "generated_internal_id": "CONT_AWD_N6600123F0928_9700_NNG15SD60B_8000"
    },
    {
        "internal_id": 163648367,
        "Award ID": "N0016423F0095",
        "Recipient Name": "AGSI, LLC",
        "Start Date": "2023-07-11",
        "End Date": "2023-07-11",
        "Award Amount": 43184.63,
        "Description": "JFROG ARTIFACTORY/XRAY LICENSES",
        "Award Type": null,
        "generated_internal_id": "CONT_AWD_N0016423F0095_9700_GS35F0622T_4730"
    },
    {
        "internal_id": 162967944,
        "Award ID": "N6600123F0763",
        "Recipient Name": "ADVANCED COMPUTER CONCEPTS, INC.",
        "Start Date": "2023-06-21",
        "End Date": "2023-07-01",
        "Award Amount": 47599.65,
        "Description": "JFROG ARTIFACTORY PRO SOFTWARE",
        "Award Type": null,
        "generated_internal_id": "CONT_AWD_N6600123F0763_9700_NNG15SD60B_8000"
    },
    {
        "internal_id": 162848324,
        "Award ID": "N6523623F0417",
        "Recipient Name": "ADVANCED COMPUTER CONCEPTS, INC.",
        "Start Date": "2023-06-16",
        "End Date": "2023-09-08",
        "Award Amount": 233808.34,
        "Description": "JFROG 8 EACH: JFROG ENTERPRISE X, 4 EACH: JFROG ENTERPRISE X. SONARSOURCE 1 EACH: SONARQUBE (WITH SUPPORT), 1 EACH: SONARQUBE (WITHOUT SUPPORT)",
        "Award Type": null,
        "generated_internal_id": "CONT_AWD_N6523623F0417_9700_NNG15SD60B_8000"
    },
    {
        "internal_id": 160323805,
        "Award ID": "80NSSC23FA632",
        "Recipient Name": "BETTER DIRECT, LLC",
        "Start Date": "2023-06-16",
        "End Date": "2024-06-15",
        "Award Amount": 66164.72,
        "Description": "JFROG ENTERPRISE X SOFTWARE AND SUPPORT ELMT STANDALONE",
        "Award Type": null,
        "generated_internal_id": "CONT_AWD_80NSSC23FA632_8000_NNG15SD45B_8000"
    },
    {
        "internal_id": 159805104,
        "Award ID": "75N92023F00114",
        "Recipient Name": "GOVSMART INC",
        "Start Date": "2023-06-05",
        "End Date": "2024-06-04",
        "Award Amount": 39436.2,
        "Description": "23-011293 NHLBI ITAC REQUIRES PURCHASE OF JFROG ENTERPRISE X SOFTWARE LICENSES IN ORDER TO SUPPLY ITAC DEVELOPERS WITH A UNIVERSAL ARTIFACT REPOSITORY TO STORE SOFTWARE PACKAGES AND FILES.",
        "Award Type": null,
        "generated_internal_id": "CONT_AWD_75N92023F00114_7529_NNG15SD11B_8000"
    },
    {
        "internal_id": 159675181,
        "Award ID": "50310223F0104",
        "Recipient Name": "SOFTWARE INFORMATION RESOURCE CORP.",
        "Start Date": "2023-06-01",
        "End Date": "2024-05-31",
        "Award Amount": 79004.7,
        "Description": "JFROG SOFTWARE LICENSE AND MAINTENANCE SUPPORT",
        "Award Type": null,
        "generated_internal_id": "CONT_AWD_50310223F0104_5000_NNG15SD74B_8000"
    },
    {
        "internal_id": 160804004,
        "Award ID": "N6600123F0485",
        "Recipient Name": "NEW TECH SOLUTIONS, INC.",
        "Start Date": "2023-05-31",
        "End Date": "2024-05-30",
        "Award Amount": 120756.0,
        "Description": "JFROG ENTERPRISE LICENSE RENEWAL",
        "Award Type": null,
        "generated_internal_id": "CONT_AWD_N6600123F0485_9700_NNG15SC82B_8000"
    },
    {
        "internal_id": 160050619,
        "Award ID": "19AQMM23F1524",
        "Recipient Name": "SOFTWARE INFORMATION RESOURCE CORP.",
        "Start Date": "2023-05-27",
        "End Date": "2024-05-26",
        "Award Amount": 45774.6,
        "Description": "JFROG ENTERPRISE, ARTIFACTORY (3 SOFTWARE LICENSES)",
        "Award Type": null,
        "generated_internal_id": "CONT_AWD_19AQMM23F1524_1900_NNG15SD74B_8000"
    },
    {
        "internal_id": 162148816,
        "Award ID": "N6449823P5206",
        "Recipient Name": "AGSI, LLC",
        "Start Date": "2023-05-19",
        "End Date": "2023-09-30",
        "Award Amount": 6601.79,
        "Description": "JFROG PRO EDITION",
        "Award Type": null,
        "generated_internal_id": "CONT_AWD_N6449823P5206_9700_-NONE-_-NONE-"
    },
    {
        "internal_id": 158567338,
        "Award ID": "70B04C23F00000413",
        "Recipient Name": "ADVANCED COMPUTER CONCEPTS, INC.",
        "Start Date": "2023-04-28",
        "End Date": "2024-04-27",
        "Award Amount": 78621.06,
        "Description": "JFROG SOFTWARE MAINTENANCE",
        "Award Type": null,
        "generated_internal_id": "CONT_AWD_70B04C23F00000413_7014_NNG15SD60B_8000"
    },
    {
        "internal_id": 158308784,
        "Award ID": "N0017823FS654",
        "Recipient Name": "ACCESSAGILITY LLC",
        "Start Date": "2023-03-26",
        "End Date": "2024-03-25",
        "Award Amount": 41989.71,
        "Description": "PART NUMBER: JFROG ENTERPRISE X",
        "Award Type": null,
        "generated_internal_id": "CONT_AWD_N0017823FS654_9700_NNG15SC23B_8000"
    },
    {
        "internal_id": 159950388,
        "Award ID": "N6426723P0098",
        "Recipient Name": "AGSI, LLC",
        "Start Date": "2023-03-15",
        "End Date": "2023-03-18",
        "Award Amount": 41199.13,
        "Description": "JFROG ENTERPRISE",
        "Award Type": null,
        "generated_internal_id": "CONT_AWD_N6426723P0098_9700_-NONE-_-NONE-"
    },
    {
        "internal_id": 159948974,
        "Award ID": "HT001523F0038",
        "Recipient Name": "BAHFED CORP",
        "Start Date": "2023-03-14",
        "End Date": "2024-03-27",
        "Award Amount": 79492.38,
        "Description": "SOFTWARE JFROG ARTIFACTORY",
        "Award Type": null,
        "generated_internal_id": "CONT_AWD_HT001523F0038_9700_NNG15SD09B_8000"
    },
    {
        "internal_id": 156433387,
        "Award ID": "697DCK23F00274",
        "Recipient Name": "MICROTECHNOLOGIES LLC",
        "Start Date": "2023-02-10",
        "End Date": "2023-03-12",
        "Award Amount": 103223.34,
        "Description": "SOFTWARE - JFROG ARTIFACTORY - JFROG ENTERPRISE X ADDITIONAL LICENSES",
        "Award Type": null,
        "generated_internal_id": "CONT_AWD_697DCK23F00274_6920_697DCK22D00002_6920"
    },
    {
        "internal_id": 159010957,
        "Award ID": "N6600123F0272",
        "Recipient Name": "ADVANCED COMPUTER CONCEPTS, INC.",
        "Start Date": "2023-02-09",
        "End Date": "2023-02-19",
        "Award Amount": 28531.44,
        "Description": "JFROG-PRO EDITION",
        "Award Type": null,
        "generated_internal_id": "CONT_AWD_N6600123F0272_9700_NNG15SD60B_8000"
    },
    {
        "internal_id": 158843193,
        "Award ID": "N6893623F0210",
        "Recipient Name": "AGSI, LLC",
        "Start Date": "2023-02-07",
        "End Date": "2024-03-28",
        "Award Amount": 42316.8,
        "Description": "JFROG ENTERPRISE X (3 LICENSE ARTIFACTOR",
        "Award Type": null,
        "generated_internal_id": "CONT_AWD_N6893623F0210_9700_GS35F0622T_4730"
    },
    {
        "internal_id": 156319702,
        "Award ID": "12314423F0092",
        "Recipient Name": "ACCESSAGILITY LLC",
        "Start Date": "2023-02-03",
        "End Date": "2024-02-10",
        "Award Amount": 38912.36,
        "Description": "JFROG ARTIFACTORY  HIGH AVAILABILITY VERSION  MULTIPUSH REPLICATION  SCIM ID SUPPORT  FEDERATED REPOSITORIES  3RD PARTY AND VAULT INTEGRATION  JFROG XRAY  PREMIUM VULNERABILITY DATABASE INCLUDED (POWERED BY VULNDB)   PROJECT-BASED MANAGEMEN",
        "Award Type": null,
        "generated_internal_id": "CONT_AWD_12314423F0092_1205_NNG15SC23B_8000"
    },
    {
        "internal_id": 156197057,
        "Award ID": "47HAA023F0019",
        "Recipient Name": "RELEASETEAM INC",
        "Start Date": "2023-01-30",
        "End Date": "2024-01-29",
        "Award Amount": 19649.37,
        "Description": "JFROG SOFTWARE RENEWAL",
        "Award Type": null,
        "generated_internal_id": "CONT_AWD_47HAA023F0019_4773_GS35F186BA_4732"
    },
    {
        "internal_id": 156227804,
        "Award ID": "N0017823FS615",
        "Recipient Name": "ACCESSAGILITY LLC",
        "Start Date": "2022-12-31",
        "End Date": "2023-12-30",
        "Award Amount": 115839.48,
        "Description": "JFROG ENTERPRISE+",
        "Award Type": null,
        "generated_internal_id": "CONT_AWD_N0017823FS615_9700_NNG15SC23B_8000"
    },
    {
        "internal_id": 157051483,
        "Award ID": "HTC71123FD033",
        "Recipient Name": "ENTERPRISE TECHNOLOGY SOLUTIONS, INC.",
        "Start Date": "2022-12-08",
        "End Date": "2022-12-15",
        "Award Amount": 42072.12,
        "Description": "JFROG ENTERPRISE X",
        "Award Type": null,
        "generated_internal_id": "CONT_AWD_HTC71123FD033_9700_NNG15SD76B_8000"
    },
    {
        "internal_id": 156508163,
        "Award ID": "N0017823FS624",
        "Recipient Name": "ENTERPRISE TECHNOLOGY SOLUTIONS, INC.",
        "Start Date": "2022-11-23",
        "End Date": "2023-11-22",
        "Award Amount": 20194.24,
        "Description": "JFROG PRO X EDITION",
        "Award Type": null,
        "generated_internal_id": "CONT_AWD_N0017823FS624_9700_NNG15SD76B_8000"
    },
    {
        "internal_id": 152636923,
        "Award ID": "2033H623F00021",
        "Recipient Name": "ADVANCED COMPUTER CONCEPTS, INC.",
        "Start Date": "2022-11-02",
        "End Date": "2023-11-01",
        "Award Amount": 29343.08,
        "Description": "JFROG PRO X EDITION ANTIFACTORY LICENSES",
        "Award Type": null,
        "generated_internal_id": "CONT_AWD_2033H623F00021_2036_NNG15SD60B_8000"
    },
    {
        "internal_id": 152079020,
        "Award ID": "2031JW22F00120",
        "Recipient Name": "BAHFED CORP",
        "Start Date": "2022-09-26",
        "End Date": "2023-09-25",
        "Award Amount": 115857.36,
        "Description": "JFROG ENTERPRISE+ SOFTWARE LICENSE AND SUPPORT",
        "Award Type": null,
        "generated_internal_id": "CONT_AWD_2031JW22F00120_2046_NNG15SD09B_8000"
    },
    {
        "internal_id": 152097106,
        "Award ID": "12314422F0818",
        "Recipient Name": "ADVANCED COMPUTER CONCEPTS, INC.",
        "Start Date": "2022-09-23",
        "End Date": "2023-09-22",
        "Award Amount": 41676.0,
        "Description": "JFROG ARIFACTORY HSTXXX0000001833",
        "Award Type": null,
        "generated_internal_id": "CONT_AWD_12314422F0818_1205_NNG15SD60B_8000"
    },
    {
        "internal_id": 151855455,
        "Award ID": "1605TB22F00118",
        "Recipient Name": "NEW TECH SOLUTIONS, INC.",
        "Start Date": "2022-09-20",
        "End Date": "2023-09-19",
        "Award Amount": 42330.0,
        "Description": "JFROG X ENTERPRISE LICENSE.",
        "Award Type": null,
        "generated_internal_id": "CONT_AWD_1605TB22F00118_1605_NNG15SC82B_8000"
    },
    {
        "internal_id": 151002432,
        "Award ID": "75N94022F00001",
        "Recipient Name": "GOVSMART INC",
        "Start Date": "2022-09-07",
        "End Date": "2023-09-06",
        "Award Amount": 55876.45,
        "Description": "THIS FIRM FIXED PRICE DELIVERY ORDER IS AWARDED IN ACCORDANCE WITH FAR 16.505 ORDERING AND, PURSUANT TO NIH CIO-CS NITAAC # HHSN316201500027W FOR  JFROG ENTERPRISE X QTY4JFROG ARTIFACTORY AND JFROG XRAY TO GOVSMART INC.,  IN THE AMOUNT OF $55,876.45",
        "Award Type": null,
        "generated_internal_id": "CONT_AWD_75N94022F00001_7529_HHSN316201500027W_7529"
    },
    {
        "internal_id": 154616730,
        "Award ID": "N0017322F1237",
        "Recipient Name": "AGSI, LLC",
        "Start Date": "2022-08-30",
        "End Date": "2022-10-07",
        "Award Amount": 40213.5,
        "Description": "JFROG ENTERPRISE X",
        "Award Type": null,
        "generated_internal_id": "CONT_AWD_N0017322F1237_9700_GS35F0622T_4730"
    },
    {
        "internal_id": 153984645,
        "Award ID": "N6600122F0931",
        "Recipient Name": "BAHFED CORP",
        "Start Date": "2022-08-30",
        "End Date": "2022-08-30",
        "Award Amount": 10729.16,
        "Description": "JFROG PRO EDITION",
        "Award Type": null,
        "generated_internal_id": "CONT_AWD_N6600122F0931_9700_NNG15SD09B_8000"
    },
    {
        "internal_id": 154387957,
        "Award ID": "N6523622F0694",
        "Recipient Name": "ENTERPRISE TECHNOLOGY SOLUTIONS, INC.",
        "Start Date": "2022-08-29",
        "End Date": "2023-08-28",
        "Award Amount": 228234.97,
        "Description": "JFROG ENTERPRISE X & SONARQUBE",
        "Award Type": null,
        "generated_internal_id": "CONT_AWD_N6523622F0694_9700_NNG15SD76B_8000"
    },
    {
        "internal_id": 151320152,
        "Award ID": "75N92022F00203",
        "Recipient Name": "ENTERPRISE TECHNOLOGY SOLUTIONS, INC.",
        "Start Date": "2022-08-17",
        "End Date": "2023-08-21",
        "Award Amount": 20154.44,
        "Description": "SD0545 ENTERPRISE TECHNOLOGY SOLUTIONS, INC.:  22-0041-P-RD-SW. JFROG ARTIFACTORY  UNLIMITED REPOSITORIES  UNIVERSAL ARTIFACT SUPPORT  CONTAINER REGISTRY  BINARY REPLICATION  REST API AND CLI AUTOMATION JFROG XRAY  VALID UNTIL 8.22.2022 - 8.22.2",
        "Award Type": null,
        "generated_internal_id": "CONT_AWD_75N92022F00203_7529_NNG15SD76B_8000"
    },
    {
        "internal_id": 152670804,
        "Award ID": "N0017822FS853",
        "Recipient Name": "OGIS COMMUNICATION GROUP, INC.",
        "Start Date": "2022-08-12",
        "End Date": "2023-08-11",
        "Award Amount": 20080.0,
        "Description": "JFROG PRO X EDITION",
        "Award Type": null,
        "generated_internal_id": "CONT_AWD_N0017822FS853_9700_NNG15SD13B_8000"
    },
    {
        "internal_id": 150653278,
        "Award ID": "70B04C22F00000827",
        "Recipient Name": "C & C INTERNATIONAL COMPUTERS & CONSULTANTS, INC.",
        "Start Date": "2022-08-08",
        "End Date": "2023-08-07",
        "Award Amount": 20955.35,
        "Description": "JFROG ARTIFACTORY PRO X TOOL",
        "Award Type": null,
        "generated_internal_id": "CONT_AWD_70B04C22F00000827_7014_HSHQDC12D00011_7001"
    },
    {
        "internal_id": 150728989,
        "Award ID": "140F0722F0103",
        "Recipient Name": "SOFTWARE INFORMATION RESOURCE CORP.",
        "Start Date": "2022-08-04",
        "End Date": "2023-08-28",
        "Award Amount": 20258.2,
        "Description": "SUPPLY: VA-JFROG ARTIFRACTORY PRO X EDITION LICENSE",
        "Award Type": null,
        "generated_internal_id": "CONT_AWD_140F0722F0103_1448_NNG15SD74B_8000"
    },
    {
        "internal_id": 150267216,
        "Award ID": "80NSSC22FA596",
        "Recipient Name": "ENTERPRISE TECHNOLOGY SOLUTIONS, INC.",
        "Start Date": "2022-07-19",
        "End Date": "2023-07-18",
        "Award Amount": 56007.08,
        "Description": "JFROG ENTERPRISE X",
        "Award Type": null,
        "generated_internal_id": "CONT_AWD_80NSSC22FA596_8000_NNG15SD76B_8000"
    },
    {
        "internal_id": 152113342,
        "Award ID": "N0017822FS839",
        "Recipient Name": "ACCESSAGILITY LLC",
        "Start Date": "2022-06-27",
        "End Date": "2022-07-11",
        "Award Amount": 41889.9,
        "Description": "JFROG ENTERPRISE X",
        "Award Type": null,
        "generated_internal_id": "CONT_AWD_N0017822FS839_9700_NNG15SC23B_8000"
    },
    {
        "internal_id": 149606547,
        "Award ID": "12760422F0279",
        "Recipient Name": "TECHTREND, INC.",
        "Start Date": "2022-06-27",
        "End Date": "2024-07-02",
        "Award Amount": 350950.04,
        "Description": "2022 STATIC CODE ANALYSIS TOOL (SONARQUBE) AND PACKAGE MANAGEMENT TOOL (JFROG ARTIFACTORY WITH JFROG XRAY) ON NRE FS DEVSECOPS PLATFORM",
        "Award Type": null,
        "generated_internal_id": "CONT_AWD_12760422F0279_12C2_GS35F0525W_4730"
    },
    {
        "internal_id": 151508329,
        "Award ID": "FA822822F9885",
        "Recipient Name": "BAHFED CORP",
        "Start Date": "2022-06-02",
        "End Date": "2022-07-16",
        "Award Amount": 64473.7,
        "Description": "PURCHASE OF JFROG ENTERPRISE RENEWAL",
        "Award Type": null,
        "generated_internal_id": "CONT_AWD_FA822822F9885_9700_NNG15SD09B_8000"
    },
    {
        "internal_id": 150472169,
        "Award ID": "N6600122F0671",
        "Recipient Name": "ACCESSAGILITY LLC",
        "Start Date": "2022-05-31",
        "End Date": "2022-06-01",
        "Award Amount": 115885.5,
        "Description": "JFROG ENT+TIER 6-9",
        "Award Type": null,
        "generated_internal_id": "CONT_AWD_N6600122F0671_9700_NNG15SC23B_8000"
    },
    {
        "internal_id": 148337973,
        "Award ID": "50310222F0069",
        "Recipient Name": "FCN INC",
        "Start Date": "2022-05-31",
        "End Date": "2023-05-31",
        "Award Amount": 73924.2,
        "Description": "JFROG ENTERPRISE X SUBSCRIPTION SOFTWARE LICENSES",
        "Award Type": null,
        "generated_internal_id": "CONT_AWD_50310222F0069_5000_50310221G0006_5000"
    },
    {
        "internal_id": 148132801,
        "Award ID": "75N92022F00118",
        "Recipient Name": "STERLING COMPUTERS CORPORATION",
        "Start Date": "2022-04-18",
        "End Date": "2023-05-07",
        "Award Amount": 20131.51,
        "Description": "NIH NHLBI ITAC SOFTWARE DEVELOPMENT TEAM REQUIRES RENEWAL OF A JFROG ARTIFACTORY PRO X  LICENSE IN ORDER TO CONTINUE TO MAINTAIN A UNIVERSAL ARTIFACT REPOSITORY.  SUPPORT SERVICES 24 AND 7 SLA BASED SUPPORT, 05/08/2022 - 05/07/2023.[22-010037]",
        "Award Type": null,
        "generated_internal_id": "CONT_AWD_75N92022F00118_7529_NNG15SC49B_8000"
    },
    {
        "internal_id": 149997229,
        "Award ID": "N6600122F0599",
        "Recipient Name": "ACCESSAGILITY LLC",
        "Start Date": "2022-04-15",
        "End Date": "2023-04-24",
        "Award Amount": 55742.4,
        "Description": "JFROG ARTIFACTORY",
        "Award Type": null,
        "generated_internal_id": "CONT_AWD_N6600122F0599_9700_NNG15SC23B_8000"
    },
    {
        "internal_id": 148807820,
        "Award ID": "N6893622F0213",
        "Recipient Name": "AGSI, LLC",
        "Start Date": "2022-03-29",
        "End Date": "2023-03-28",
        "Award Amount": 36275.09,
        "Description": "JFROG ENTERPRISE SOFTWARE RENEWAL",
        "Award Type": null,
        "generated_internal_id": "CONT_AWD_N6893622F0213_9700_GS35F0622T_4730"
    },
    {
        "internal_id": 149424240,
        "Award ID": "N0017822FS690",
        "Recipient Name": "BAHFED CORP",
        "Start Date": "2022-03-23",
        "End Date": "2022-04-22",
        "Award Amount": 40051.02,
        "Description": "PART NUMBER: JFROG ENTERPRISE X",
        "Award Type": null,
        "generated_internal_id": "CONT_AWD_N0017822FS690_9700_NNG15SD09B_8000"
    },
    {
        "internal_id": 149289960,
        "Award ID": "N6426722F0122",
        "Recipient Name": "ACCESSAGILITY LLC",
        "Start Date": "2022-03-16",
        "End Date": "2022-03-25",
        "Award Amount": 41898.39,
        "Description": "JFROG ENTERPRISEX",
        "Award Type": null,
        "generated_internal_id": "CONT_AWD_N6426722F0122_9700_NNG15SC23B_8000"
    },
    {
        "internal_id": 146153192,
        "Award ID": "47HAA022F0041",
        "Recipient Name": "ACCESSAGILITY LLC",
        "Start Date": "2022-02-26",
        "End Date": "2023-02-25",
        "Award Amount": 41944.05,
        "Description": "JFROG RENEWAL",
        "Award Type": null,
        "generated_internal_id": "CONT_AWD_47HAA022F0041_4773_NNG15SC23B_8000"
    },
    {
        "internal_id": 147521186,
        "Award ID": "N6600122F0272",
        "Recipient Name": "KPAUL PROPERTIES LLC",
        "Start Date": "2022-01-06",
        "End Date": "2023-01-05",
        "Award Amount": 10404.04,
        "Description": "JFROG SUBSCRIPTION LICENSE RENEWAL",
        "Award Type": null,
        "generated_internal_id": "CONT_AWD_N6600122F0272_9700_NNG15SD33B_8000"
    },
    {
        "internal_id": 146181583,
        "Award ID": "N0017822FS600",
        "Recipient Name": "OGIS COMMUNICATION GROUP, INC.",
        "Start Date": "2021-12-31",
        "End Date": "2022-12-31",
        "Award Amount": 115920.0,
        "Description": "JFROG-ENTERPRISE+",
        "Award Type": null,
        "generated_internal_id": "CONT_AWD_N0017822FS600_9700_NNG15SD13B_8000"
    },
    {
        "internal_id": 145050204,
        "Award ID": "75N97022F00001",
        "Recipient Name": "IDEAL SYSTEM SOLUTIONS, INC.",
        "Start Date": "2021-12-30",
        "End Date": "2022-03-05",
        "Award Amount": 56221.09,
        "Description": "ANNUAL SOFTWARE AGREEMENT - JFROG ENTERPRISE UPGRADE",
        "Award Type": null,
        "generated_internal_id": "CONT_AWD_75N97022F00001_7529_HHSN316201500028W_7529"
    },
    {
        "internal_id": 146731839,
        "Award ID": "HTC71122FD020",
        "Recipient Name": "GOVSMART, INC.",
        "Start Date": "2021-12-15",
        "End Date": "2022-12-14",
        "Award Amount": 41645.28,
        "Description": "JFROG ENTERPRISE X",
        "Award Type": null,
        "generated_internal_id": "CONT_AWD_HTC71122FD020_9700_NNG15SD11B_8000"
    },
    {
        "internal_id": 146332371,
        "Award ID": "N0017822FS619",
        "Recipient Name": "ENTERPRISE TECHNOLOGY SOLUTIONS, INC.",
        "Start Date": "2021-11-23",
        "End Date": "2022-11-22",
        "Award Amount": 20174.34,
        "Description": "JFROG PRO X EDITION",
        "Award Type": null,
        "generated_internal_id": "CONT_AWD_N0017822FS619_9700_NNG15SD76B_8000"
    },
    {
        "internal_id": 140712293,
        "Award ID": "2033H622F00019",
        "Recipient Name": "ARCHITECHTURE SOLUTIONS LLC",
        "Start Date": "2021-11-02",
        "End Date": "2022-11-01",
        "Award Amount": 29492.0,
        "Description": "NEW CONTRACT TO PURCHASE JFROG PRO X EDITION - ANTIFACTORY LICENSES (RENEWAL 2033H621F0038).",
        "Award Type": null,
        "generated_internal_id": "CONT_AWD_2033H622F00019_2036_NNG15SD42B_8000"
    },
    {
        "internal_id": 139448126,
        "Award ID": "1605TB21F00121",
        "Recipient Name": "OGIS COMMUNICATION GROUP, INC.",
        "Start Date": "2021-09-20",
        "End Date": "2022-09-19",
        "Award Amount": 41744.85,
        "Description": "JFROG X ENTERPRISE LICENSE. POP SEPTEMBER 20, 2021 THROUGH SEPTEMBER 19, 2022.",
        "Award Type": null,
        "generated_internal_id": "CONT_AWD_1605TB21F00121_1605_NNG15SD13B_8000"
    },
    {
        "internal_id": 140471369,
        "Award ID": "N6523621F0586",
        "Recipient Name": "NEW TECH SOLUTIONS, INC.",
        "Start Date": "2021-09-16",
        "End Date": "2022-08-31",
        "Award Amount": 100496.4,
        "Description": "ENTERPRISE X JFROG",
        "Award Type": null,
        "generated_internal_id": "CONT_AWD_N6523621F0586_9700_NNG15SC82B_8000"
    },
    {
        "internal_id": 144422831,
        "Award ID": "N6600121F09A8",
        "Recipient Name": "ENTERPRISE TECHNOLOGY SOLUTIONS, INC.",
        "Start Date": "2021-09-15",
        "End Date": "2022-08-17",
        "Award Amount": 75655.14,
        "Description": "JFROG ENTERPRISE X",
        "Award Type": null,
        "generated_internal_id": "CONT_AWD_N6600121F09A8_9700_NNG15SD76B_8000"
    },
    {
        "internal_id": 139052973,
        "Award ID": "75N94021F00010",
        "Recipient Name": "IT1 SOURCE LLC",
        "Start Date": "2021-09-07",
        "End Date": "2022-09-06",
        "Award Amount": 56310.04,
        "Description": "THIS FIRM FIXED PRICE DELIVERY ORDER IS AWARDED IN ACCORDANCE WITH FAR 16.505 ORDERING AND, PURSUANT TO NIH CIO-CS NITAAC # HHSN316201500059W FOR JFROG ENTERPRISE X INCLUDES JFROG ARTIFACTORY & XRAY ALSO INCLUDES SUPPORT SERVICES TO IT1 SOURCE,",
        "Award Type": null,
        "generated_internal_id": "CONT_AWD_75N94021F00010_7529_HHSN316201500059W_7529"
    },
    {
        "internal_id": 139569677,
        "Award ID": "697DCK21F01243",
        "Recipient Name": "CDW GOVERNMENT LLC",
        "Start Date": "2021-08-30",
        "End Date": "2021-10-23",
        "Award Amount": 47496.66,
        "Description": "THE PURCHASE OF JFROG ARTIFACTORY ENTERPRISE LICENSE RENEWAL FOR SOFTWARE MANAGEMENT AND DISTRIBUTION TASKING AND MAINTAINING TASKING.",
        "Award Type": null,
        "generated_internal_id": "CONT_AWD_697DCK21F01243_6920_DTFACT13D00004_6920"
    },
    {
        "internal_id": 143479282,
        "Award ID": "FA822821F9258",
        "Recipient Name": "ENTERPRISE TECHNOLOGY SOLUTIONS, INC.",
        "Start Date": "2021-08-18",
        "End Date": "2021-09-18",
        "Award Amount": 63077.5,
        "Description": "PURCHASE OF CYBEROPS: JFROG ENTERPRISE  RENEWAL",
        "Award Type": null,
        "generated_internal_id": "CONT_AWD_FA822821F9258_9700_NNG15SD76B_8000"
    },
    {
        "internal_id": 143467969,
        "Award ID": "N0017821FS975",
        "Recipient Name": "BAHFED CORP",
        "Start Date": "2021-08-17",
        "End Date": "2022-08-11",
        "Award Amount": 20098.98,
        "Description": "JFROG ARTIFACTORY",
        "Award Type": null,
        "generated_internal_id": "CONT_AWD_N0017821FS975_9700_NNG15SD09B_8000"
    },
    {
        "internal_id": 138824773,
        "Award ID": "70B04C21F00000950",
        "Recipient Name": "C & C INTERNATIONAL COMPUTERS & CONSULTANTS, INC.",
        "Start Date": "2021-08-08",
        "End Date": "2022-08-07",
        "Award Amount": 20749.35,
        "Description": "JFROG SOFTWARE",
        "Award Type": null,
        "generated_internal_id": "CONT_AWD_70B04C21F00000950_7014_HSHQDC12D00011_7001"
    },
    {
        "internal_id": 138634608,
        "Award ID": "75N92021F00209",
        "Recipient Name": "KPAUL PROPERTIES LLC",
        "Start Date": "2021-07-28",
        "End Date": "2022-08-23",
        "Award Amount": 20101.01,
        "Description": "THE ITAC SOFTWARE DEVELOPMENT TEAM REQUIRES A JFROG ARTIFACTORY PRO X LICENSE IN ORDER TO MAINTAIN A UNIVERSAL ARTIFACT REPOSITORY.",
        "Award Type": null,
        "generated_internal_id": "CONT_AWD_75N92021F00209_7529_NNG15SD33B_8000"
    },
    {
        "internal_id": 138344726,
        "Award ID": "140F0721P0047",
        "Recipient Name": "AGSI, LLC",
        "Start Date": "2021-07-21",
        "End Date": "2021-08-20",
        "Award Amount": 19755.73,
        "Description": "SUPPLY:  CO-ECOS-JFROG ARTIFACTORY PRO X EDITION",
        "Award Type": null,
        "generated_internal_id": "CONT_AWD_140F0721P0047_1448_-NONE-_-NONE-"
    },
    {
        "internal_id": 137880476,
        "Award ID": "12314421F0493",
        "Recipient Name": "NEW TECH SOLUTIONS, INC.",
        "Start Date": "2021-07-14",
        "End Date": "2021-07-24",
        "Award Amount": 41728.25,
        "Description": "FY21 JFROG ARTIFACTORY ENTERPRISE X SOFTWARE MAINTENANCE & SUPPORT RENEWAL POP: 8/1/2021-7/31/2022",
        "Award Type": null,
        "generated_internal_id": "CONT_AWD_12314421F0493_1205_NNG15SC82B_8000"
    },
    {
        "internal_id": 139296447,
        "Award ID": "N6523621F0442",
        "Recipient Name": "ACCESSAGILITY LLC",
        "Start Date": "2021-06-30",
        "End Date": "2022-06-30",
        "Award Amount": 19890.76,
        "Description": "JF-PROX-EDITION JFROG ARTIFACTORY UNLIMI",
        "Award Type": null,
        "generated_internal_id": "CONT_AWD_N6523621F0442_9700_NNG15SC23B_8000"
    },
    {
        "internal_id": 139815928,
        "Award ID": "N6600121F0803",
        "Recipient Name": "ARCHITECHTURE SOLUTIONS LLC",
        "Start Date": "2021-06-14",
        "End Date": "2022-06-26",
        "Award Amount": 10460.0,
        "Description": "JFROG PRO EDITION RENEWAL",
        "Award Type": null,
        "generated_internal_id": "CONT_AWD_N6600121F0803_9700_NNG15SD42B_8000"
    },
    {
        "internal_id": 132998268,
        "Award ID": "50310221F0059",
        "Recipient Name": "FCN INC",
        "Start Date": "2021-05-31",
        "End Date": "2022-05-31",
        "Award Amount": 42229.5,
        "Description": "JFROG ENTERPRISE X SOFTWARE MAINTENANCE",
        "Award Type": null,
        "generated_internal_id": "CONT_AWD_50310221F0059_5000_50310221G0006_5000"
    },
    {
        "internal_id": 134014733,
        "Award ID": "75N97021F00019",
        "Recipient Name": "IT1 SOURCE LLC",
        "Start Date": "2021-05-23",
        "End Date": "2022-05-22",
        "Award Amount": 27313.54,
        "Description": "JFROG ENTERPRISE - ANNUAL SOFTWARE RENEWAL",
        "Award Type": null,
        "generated_internal_id": "CONT_AWD_75N97021F00019_7529_HHSN316201500059W_7529"
    },
    {
        "internal_id": 130325313,
        "Award ID": "70B04C21F00000377",
        "Recipient Name": "BAHFED CORP",
        "Start Date": "2021-04-28",
        "End Date": "2022-04-27",
        "Award Amount": 76030.56,
        "Description": "JFROG SOFTWARE MAINTENANCE",
        "Award Type": null,
        "generated_internal_id": "CONT_AWD_70B04C21F00000377_7014_NNG15SD09B_8000"
    },
    {
        "internal_id": 131684652,
        "Award ID": "75N92021F00140",
        "Recipient Name": "GOVSMART INC",
        "Start Date": "2021-04-23",
        "End Date": "2021-04-28",
        "Award Amount": 20198.5,
        "Description": "THE ITAC SOFTWARE DEVELOPMENT TEAM REQUIRES A JFROG ARTIFACTORY PRO X LICENSE IN ORDER TO CONTINUE TO MAINTAIN A UNIVERSAL ARTIFACT REPOSITORY.",
        "Award Type": null,
        "generated_internal_id": "CONT_AWD_75N92021F00140_7529_NNG15SD11B_8000"
    },
    {
        "internal_id": 138349020,
        "Award ID": "N6600121F0558",
        "Recipient Name": "MVS, INC.",
        "Start Date": "2021-04-22",
        "End Date": "2022-04-21",
        "Award Amount": 56042.92,
        "Description": "JFROG ENTERPRISE EDITION",
        "Award Type": null,
        "generated_internal_id": "CONT_AWD_N6600121F0558_9700_NNG15SD12B_8000"
    },
    {
        "internal_id": 137344656,
        "Award ID": "N6893621P0209",
        "Recipient Name": "GOVSMART INC",
        "Start Date": "2021-03-25",
        "End Date": "2022-03-31",
        "Award Amount": 20373.6,
        "Description": "JFROG ENTERPRISE X LICENSES RENEWAL - QTY 3 EA",
        "Award Type": null,
        "generated_internal_id": "CONT_AWD_N6893621P0209_9700_-NONE-_-NONE-"
    },
    {
        "internal_id": 125299925,
        "Award ID": "47HAA021F0034",
        "Recipient Name": "AGSI, LLC",
        "Start Date": "2021-03-01",
        "End Date": "2022-02-28",
        "Award Amount": 40509.19,
        "Description": "FY21 JFROG LICENSE",
        "Award Type": null,
        "generated_internal_id": "CONT_AWD_47HAA021F0034_4773_GS35F0622T_4730"
    },
    {
        "internal_id": 130182568,
        "Award ID": "FA440721F0092",
        "Recipient Name": "STERLING COMPUTERS CORPORATION",
        "Start Date": "2021-01-11",
        "End Date": "2022-01-19",
        "Award Amount": 42346.92,
        "Description": "FY21 JFROG ARTIFACTORY ENTERPRISE SOFTWARE",
        "Award Type": null,
        "generated_internal_id": "CONT_AWD_FA440721F0092_9700_NNG15SC20B_8000"
    },
    {
        "internal_id": 130161784,
        "Award ID": "N0017821FS644",
        "Recipient Name": "SOFTWARE INFORMATION RESOURCE CORP.",
        "Start Date": "2021-01-08",
        "End Date": "2022-01-07",
        "Award Amount": 115862.5,
        "Description": "JFROG-ENTERPRISE+",
        "Award Type": null,
        "generated_internal_id": "CONT_AWD_N0017821FS644_9700_NNG15SD74B_8000"
    },
    {
        "internal_id": 127884478,
        "Award ID": "N0017321F0801",
        "Recipient Name": "RELEASETEAM INC",
        "Start Date": "2020-12-11",
        "End Date": "2020-12-15",
        "Award Amount": 14400.0,
        "Description": "JFROG PRO X EDITION 12 MTHS",
        "Award Type": null,
        "generated_internal_id": "CONT_AWD_N0017321F0801_9700_GS35F186BA_4732"
    },
    {
        "internal_id": 116168444,
        "Award ID": "80NSSC21F0224",
        "Recipient Name": "OGIS COMMUNICATION GROUP, INC.",
        "Start Date": "2020-11-27",
        "End Date": "2021-11-26",
        "Award Amount": 14560.0,
        "Description": "OT S5B-173897 175514 JFROG PRO X EDITION",
        "Award Type": null,
        "generated_internal_id": "CONT_AWD_80NSSC21F0224_8000_NNG15SD13B_8000"
    },
    {
        "internal_id": 111363016,
        "Award ID": "2033H621F00038",
        "Recipient Name": "MVS, INC.",
        "Start Date": "2020-10-27",
        "End Date": "2021-11-01",
        "Award Amount": 19411.16,
        "Description": "JFROG JFROG PRO X EDITION - ARTIFACTORY PRO LICENSE",
        "Award Type": null,
        "generated_internal_id": "CONT_AWD_2033H621F00038_2036_NNG15SD12B_8000"
    },
    {
        "internal_id": 110733930,
        "Award ID": "140F0920P0061",
        "Recipient Name": "RELEASETEAM INC",
        "Start Date": "2020-10-01",
        "End Date": "2021-09-30",
        "Award Amount": 13580.0,
        "Description": "CO-ECOS-JFROG PRO X EDITION",
        "Award Type": null,
        "generated_internal_id": "CONT_AWD_140F0920P0061_1448_-NONE-_-NONE-"
    },
    {
        "internal_id": 116615089,
        "Award ID": "HC102820F1592",
        "Recipient Name": "NORSEMAN INC",
        "Start Date": "2020-09-29",
        "End Date": "2021-09-28",
        "Award Amount": 31216.93,
        "Description": "JFROG, INC.",
        "Award Type": null,
        "generated_internal_id": "CONT_AWD_HC102820F1592_9700_NNG15SC83B_8000"
    },
    {
        "internal_id": 110177920,
        "Award ID": "15JUST20F00000363",
        "Recipient Name": "AGSI, LLC",
        "Start Date": "2020-09-09",
        "End Date": "2021-09-08",
        "Award Amount": 14049.36,
        "Description": "JFROG PRO X EDITION ARTIFACTORY PRO LICENSE VERSION 1 RENEWAL",
        "Award Type": null,
        "generated_internal_id": "CONT_AWD_15JUST20F00000363_1501_GS35F0622T_4730"
    },
    {
        "internal_id": 116038813,
        "Award ID": "N6600120F1224",
        "Recipient Name": "RELEASETEAM INC",
        "Start Date": "2020-09-03",
        "End Date": "2021-09-02",
        "Award Amount": 73759.2,
        "Description": "JFROG ENTERPRISE EDITION SA",
        "Award Type": null,
        "generated_internal_id": "CONT_AWD_N6600120F1224_9700_GS35F186BA_4732"
    },
    {
        "internal_id": 115967676,
        "Award ID": "N6600120F1144",
        "Recipient Name": "BAHFED CORP",
        "Start Date": "2020-09-01",
        "End Date": "2020-09-01",
        "Award Amount": 57087.1,
        "Description": "JFROG JFROG ENTERPRISE ED ARTIFACTORY",
        "Award Type": null,
        "generated_internal_id": "CONT_AWD_N6600120F1144_9700_NNG15SD09B_8000"
    },
    {
        "internal_id": 115950729,
        "Award ID": "N6893620P0595",
        "Recipient Name": "AGSI, LLC",
        "Start Date": "2020-08-31",
        "End Date": "2020-09-11",
        "Award Amount": 23544.0,
        "Description": "JFROG PRO X EDITION (2 LICENSES)",
        "Award Type": null,
        "generated_internal_id": "CONT_AWD_N6893620P0595_9700_-NONE-_-NONE-"
    },
    {
        "internal_id": 109354712,
        "Award ID": "12314420F0550",
        "Recipient Name": "OGIS COMMUNICATION GROUP, INC.",
        "Start Date": "2020-08-28",
        "End Date": "2020-09-20",
        "Award Amount": 29925.0,
        "Description": "FY20 IOD IOSB JFROG ARTIFACTORY SOFTWARE RENEWAL AS A PRODUCT.",
        "Award Type": null,
        "generated_internal_id": "CONT_AWD_12314420F0550_1205_NNG15SD13B_8000"
    },
    {
        "internal_id": 109314077,
        "Award ID": "692M1520F00541",
        "Recipient Name": "CDW GOVERNMENT LLC",
        "Start Date": "2020-08-26",
        "End Date": "2021-08-30",
        "Award Amount": 47495.01,
        "Description": "JFROG ARTIFACTORY ENTERPRISE LICENSE FOR SERVERS.",
        "Award Type": null,
        "generated_internal_id": "CONT_AWD_692M1520F00541_6920_DTFACT13D00004_6920"
    },
    {
        "internal_id": 108838207,
        "Award ID": "75N92020F00225",
        "Recipient Name": "ARCHITECHTURE SOLUTIONS LLC",
        "Start Date": "2020-08-19",
        "End Date": "2021-08-23",
        "Award Amount": 14587.0,
        "Description": "TS13668 / 20-013668  NHLBI ITAC DEVELOPMENT TEAM REQUIRES PURCHASE OF AN ADDITIONAL JFROG ARTIFACTORY PRO X SOFTWARE LICENSE IN ORDER TO MAINTAIN A UNIVERSAL ARTIFACT REPOSITORY.",
        "Award Type": null,
        "generated_internal_id": "CONT_AWD_75N92020F00225_7529_NNG15SD94B_8000"
    },
    {
        "internal_id": 111724198,
        "Award ID": "N0017820FS906",
        "Recipient Name": "ENTERPRISE TECHNOLOGY SOLUTIONS, INC.",
        "Start Date": "2020-08-12",
        "End Date": "2021-08-11",
        "Award Amount": 14657.2,
        "Description": "JFROG PRO X EDITION",
        "Award Type": null,
        "generated_internal_id": "CONT_AWD_N0017820FS906_9700_NNG15SD76B_8000"
    },
    {
        "internal_id": 98341450,
        "Award ID": "70B04C20F00000658",
        "Recipient Name": "FS PARTNERS LLP",
        "Start Date": "2020-08-08",
        "End Date": "2021-08-07",
        "Award Amount": 14989.84,
        "Description": "JFROG SOFTWARE RENEWAL",
        "Award Type": null,
        "generated_internal_id": "CONT_AWD_70B04C20F00000658_7014_HSHQDC13D00020_7001"
    },
    {
        "internal_id": 111506541,
        "Award ID": "FA877220F2002",
        "Recipient Name": "RELEASETEAM INC",
        "Start Date": "2020-07-30",
        "End Date": "2021-07-29",
        "Award Amount": 54639.08,
        "Description": "CLOUD ONE JFROG ARTIFACTORY ENTERPRISE EDITION AND XRAY LICENSES AND SERVICES",
        "Award Type": null,
        "generated_internal_id": "CONT_AWD_FA877220F2002_9700_GS35F186BA_4732"
    },
    {
        "internal_id": 111349376,
        "Award ID": "FA822420F8302",
        "Recipient Name": "SOFTWARE INFORMATION RESOURCE CORP.",
        "Start Date": "2020-07-28",
        "End Date": "2020-08-28",
        "Award Amount": 62971.3,
        "Description": "PURCHASE OF JFROG ENTERPRISE",
        "Award Type": null,
        "generated_internal_id": "CONT_AWD_FA822420F8302_9700_NNG15SD74B_8000"
    },
    {
        "internal_id": 101893291,
        "Award ID": "12760420P0032",
        "Recipient Name": "STS SOLUTIONS AND TRAINING, LLC",
        "Start Date": "2020-07-21",
        "End Date": "2021-08-07",
        "Award Amount": 32598.3,
        "Description": "STS SOLUTIONS AND TRAINING, LLC  JFROG ARTIFACTORY SERVER LICENSES WITH SUPPORT&MAINTENANCE RENEWAL",
        "Award Type": null,
        "generated_internal_id": "CONT_AWD_12760420P0032_12C2_-NONE-_-NONE-"
    },
    {
        "internal_id": 110781010,
        "Award ID": "N6523620F0599",
        "Recipient Name": "OGIS COMMUNICATION GROUP, INC.",
        "Start Date": "2020-07-01",
        "End Date": "2021-06-30",
        "Award Amount": 14560.0,
        "Description": "JFROG PRO X EDITION",
        "Award Type": null,
        "generated_internal_id": "CONT_AWD_N6523620F0599_9700_NNG15SD13B_8000"
    },
    {
        "internal_id": 98317104,
        "Award ID": "12314420F0366",
        "Recipient Name": "OGIS COMMUNICATION GROUP, INC.",
        "Start Date": "2020-06-26",
        "End Date": "2020-08-01",
        "Award Amount": 32665.0,
        "Description": "ARTIFACTORY SOFTWARE NEW/RENEWAL LICENSES JFROG.",
        "Award Type": null,
        "generated_internal_id": "CONT_AWD_12314420F0366_1205_NNG15SD13B_8000"
    },
    {
        "internal_id": 110070313,
        "Award ID": "N6600120F0705",
        "Recipient Name": "OGIS COMMUNICATION GROUP, INC.",
        "Start Date": "2020-06-04",
        "End Date": "2020-06-30",
        "Award Amount": 9650.0,
        "Description": "JFROG PRO EDITION",
        "Award Type": null,
        "generated_internal_id": "CONT_AWD_N6600120F0705_9700_NNG15SD13B_8000"
    },
    {
        "internal_id": 97510834,
        "Award ID": "75N97020F00007",
        "Recipient Name": "IDEAL SYSTEM SOLUTIONS, INC.",
        "Start Date": "2020-05-18",
        "End Date": "2021-05-22",
        "Award Amount": 30172.44,
        "Description": "JFROG ARTIFACTORY ENTERPRISE EDITION LICENSE RENEWAL",
        "Award Type": null,
        "generated_internal_id": "CONT_AWD_75N97020F00007_7529_HHSN316201500028W_7529"
    },
    {
        "internal_id": 97280370,
        "Award ID": "75N92020F00158",
        "Recipient Name": "NEW TECH SOLUTIONS, INC.",
        "Start Date": "2020-05-15",
        "End Date": "2021-05-06",
        "Award Amount": 14889.6,
        "Description": "THE NHLBI ITAC DEVELOPMENT TEAM REQUIRES RENEWAL OF JFROG ARTIFACTORY PRO X IN ORDER TO ALLOW THEM TO CONTINUE USING IT FOR AN ARTIFACT REPOSITORY.",
        "Award Type": null,
        "generated_internal_id": "CONT_AWD_75N92020F00158_7529_NNG15SC82B_8000"
    },
    {
        "internal_id": 97218468,
        "Award ID": "50310220F0101",
        "Recipient Name": "SOFTWARE INFORMATION RESOURCE CORP.",
        "Start Date": "2020-05-13",
        "End Date": "2021-05-31",
        "Award Amount": 41873.5,
        "Description": "JFROG SOFTWARE LICENSES AND MAINTENANCE",
        "Award Type": null,
        "generated_internal_id": "CONT_AWD_50310220F0101_5000_NNG15SD74B_8000"
    },
    {
        "internal_id": 96814278,
        "Award ID": "70B04C20F00000357",
        "Recipient Name": "BLUE TECH INC.",
        "Start Date": "2020-04-28",
        "End Date": "2021-04-28",
        "Award Amount": 77999.98,
        "Description": "JFROG ENTERPRISE SW AND MAINTENANCE",
        "Award Type": null,
        "generated_internal_id": "CONT_AWD_70B04C20F00000357_7014_HSHQDC12D00012_7001"
    },
    {
        "internal_id": 90296844,
        "Award ID": "692M1520F00017",
        "Recipient Name": "CDW GOVERNMENT LLC",
        "Start Date": "2019-11-13",
        "End Date": "2020-11-13",
        "Award Amount": 17892.63,
        "Description": "JFROG BINTRAY ENTERPRISE UNIVERSAL SUPPORT - SOFTWARE.",
        "Award Type": null,
        "generated_internal_id": "CONT_AWD_692M1520F00017_6920_DTFACT13D00004_6920"
    },
    {
        "internal_id": 92498764,
        "Award ID": "N6600119P6460",
        "Recipient Name": "INSIGHT PUBLIC SECTOR, INC.",
        "Start Date": "2019-08-28",
        "End Date": "2019-09-06",
        "Award Amount": 9757.32,
        "Description": "JFROG ARTIFACTORY PRO 6.X",
        "Award Type": null,
        "generated_internal_id": "CONT_AWD_N6600119P6460_9700_-NONE-_-NONE-"
    },
    {
        "internal_id": 86980307,
        "Award ID": "692M1519F00499",
        "Recipient Name": "CDW GOVERNMENT LLC",
        "Start Date": "2019-08-21",
        "End Date": "2020-08-30",
        "Award Amount": 42500.1,
        "Description": "JFROG ARTIFACTORY ENTERPRISE AND JFROG XRAY SOFTWARE LICENSING.",
        "Award Type": null,
        "generated_internal_id": "CONT_AWD_692M1519F00499_6920_DTFACT13D00004_6920"
    },
    {
        "internal_id": 83775879,
        "Award ID": "75N94019F00129",
        "Recipient Name": "IT1 SOURCE LLC",
        "Start Date": "2019-08-20",
        "End Date": "2020-09-14",
        "Award Amount": 114132.27,
        "Description": "JFROG ENTERPRISE EDITION- ARTIFACTORY ENTERPRISE LICENSE  BASE  AND TWO OPTION YEARS",
        "Award Type": null,
        "generated_internal_id": "CONT_AWD_75N94019F00129_7529_HHSN316201500059W_7529"
    },
    {
        "internal_id": 87059576,
        "Award ID": "70B04C19F00000704",
        "Recipient Name": "BLUE TECH INC.",
        "Start Date": "2019-08-08",
        "End Date": "2020-08-07",
        "Award Amount": 15000.0,
        "Description": "JFROG SOFTWARE AND MAINTENANCE",
        "Award Type": null,
        "generated_internal_id": "CONT_AWD_70B04C19F00000704_7014_HSHQDC12D00012_7001"
    },
    {
        "internal_id": 87244416,
        "Award ID": "12760419P0024",
        "Recipient Name": "STS SOLUTIONS AND TRAINING, LLC",
        "Start Date": "2019-07-12",
        "End Date": "2020-08-07",
        "Award Amount": 32598.3,
        "Description": "STS SOLUTIONS AND TRAINING; JFROG ARTIFACTORY SOFTWARE LICENSE AND MAINTENANCE RENEWAL.",
        "Award Type": null,
        "generated_internal_id": "CONT_AWD_12760419P0024_12C2_-NONE-_-NONE-"
    },
    {
        "internal_id": 87840778,
        "Award ID": "75N97019F00089",
        "Recipient Name": "NEW TECH SOLUTIONS, INC.",
        "Start Date": "2019-05-23",
        "End Date": "2020-05-22",
        "Award Amount": 29988.07,
        "Description": "IGF::OT::IGF JFROG ARTIFACTORY ENTERPRISE",
        "Award Type": null,
        "generated_internal_id": "CONT_AWD_75N97019F00089_7529_HHSN316201500040W_7529"
    },
    {
        "internal_id": 88097700,
        "Award ID": "75N92019F00157",
        "Recipient Name": "NEW TECH SOLUTIONS, INC.",
        "Start Date": "2019-05-02",
        "End Date": "2020-05-01",
        "Award Amount": 14688.0,
        "Description": "THE NHLBI ITAC DEVELOPMENT TEAM REQUIRES RENEWAL OF JFROG ARTIFACTORY PRO X IN ORDER TO ALLOW THEM TO CONTINUE USING IT FOR AN ARTIFACT REPOSITORY.",
        "Award Type": null,
        "generated_internal_id": "CONT_AWD_75N92019F00157_7529_NNG15SC82B_8000"
    },
    {
        "internal_id": 88298155,
        "Award ID": "70B04C19F00000232",
        "Recipient Name": "BLUE TECH INC.",
        "Start Date": "2019-04-27",
        "End Date": "2020-04-28",
        "Award Amount": 76075.0,
        "Description": "JFROG ARTIFACTORY SW LICENSES AND MAINTENANCE",
        "Award Type": null,
        "generated_internal_id": "CONT_AWD_70B04C19F00000232_7014_HSHQDC12D00012_7001"
    },
    {
        "internal_id": 68631745,
        "Award ID": "1605DC18F00373",
        "Recipient Name": "RELEASETEAM INC",
        "Start Date": "2018-09-21",
        "End Date": "2021-09-19",
        "Award Amount": 104805.38,
        "Description": "JFROG ARTIFACTORY SOFTWARE LICENSE SUBSCRIPTION",
        "Award Type": null,
        "generated_internal_id": "CONT_AWD_1605DC18F00373_1605_GS35F186BA_4732"
    },
    {
        "internal_id": 88933930,
        "Award ID": "75N97018F00120",
        "Recipient Name": "IT1 SOURCE LLC",
        "Start Date": "2018-07-05",
        "End Date": "2019-09-14",
        "Award Amount": 14251.27,
        "Description": "JFROG LICENSES AND SUPPORT RENEWAL",
        "Award Type": null,
        "generated_internal_id": "CONT_AWD_75N97018F00120_7529_HHSN316201500059W_7529"
    },
    {
        "internal_id": 65698153,
        "Award ID": "70B04C18F00000273",
        "Recipient Name": "BLUE TECH INC.",
        "Start Date": "2018-04-28",
        "End Date": "2019-04-27",
        "Award Amount": 42695.0,
        "Description": "JFROG SOFTWARE MAINTENANCE",
        "Award Type": null,
        "generated_internal_id": "CONT_AWD_70B04C18F00000273_7014_HSHQDC13D00019_7001"
    },
    {
        "internal_id": 31977636,
        "Award ID": "TFSAISS170038",
        "Recipient Name": "BAHFED CORP",
        "Start Date": "2017-09-24",
        "End Date": "2018-09-23",
        "Award Amount": 6111.12,
        "Description": "JFROG ARTIFACTORY PRO LICENSE SUBSCRIPTION&MAINTENANCE",
        "Award Type": null,
        "generated_internal_id": "CONT_AWD_TFSAISS170038_2036_-NONE-_-NONE-"
    },
    {
        "internal_id": 23519358,
        "Award ID": "HHSN27600154",
        "Recipient Name": "STERLING COMPUTERS CORPORATION",
        "Start Date": "2017-07-05",
        "End Date": "2018-09-18",
        "Award Amount": 13966.21,
        "Description": "IGF::OT::IGF  JFROG ARTIFACTORY SOFTWARE LICENSE SUBSCRIPTION RENEWAL NITAAC CONTRACT HHSN316201500043W QUOTE Q-00144656 DATED JUNE 5, 2017",
        "Award Type": null,
        "generated_internal_id": "CONT_AWD_HHSN27600154_7529_HHSN316201500043W_7529"
    },
    {
        "internal_id": 23783426,
        "Award ID": "HSBP1017J00217",
        "Recipient Name": "ANACAPA MICRO PRODUCTS, INC.",
        "Start Date": "2017-04-28",
        "End Date": "2018-04-27",
        "Award Amount": 33314.0,
        "Description": "JFROG ENTERPRISE LICENSES",
        "Award Type": null,
        "generated_internal_id": "CONT_AWD_HSBP1017J00217_7014_HSHQDC12D00014_7001"
    },
    {
        "internal_id": 23518845,
        "Award ID": "HHSN27600061",
        "Recipient Name": "NEW TECH SOLUTIONS, INC.",
        "Start Date": "2016-12-12",
        "End Date": "2017-12-13",
        "Award Amount": 8228.7,
        "Description": "IGF::OT::IGF IS - NEW TECH SOLUTIONS - JFROG ARTIFACTORY SW",
        "Award Type": null,
        "generated_internal_id": "CONT_AWD_HHSN27600061_7529_HHSN316201500040W_7529"
    },
    {
        "internal_id": 31977474,
        "Award ID": "TFSAISS160029",
        "Recipient Name": "BAHFED CORP",
        "Start Date": "2016-09-24",
        "End Date": "2017-09-23",
        "Award Amount": 5156.24,
        "Description": "JFROG LICENSES",
        "Award Type": null,
        "generated_internal_id": "CONT_AWD_TFSAISS160029_2036_-NONE-_-NONE-"
    },
    {
        "internal_id": 31978156,
        "Award ID": "TFSAOIT150044",
        "Recipient Name": "SHI INTERNATIONAL CORP",
        "Start Date": "2015-09-24",
        "End Date": "2016-09-23",
        "Award Amount": 5103.1,
        "Description": "JFROG ARTIFACTORY PRO LICENSE SUBSCRIPTION",
        "Award Type": null,
        "generated_internal_id": "CONT_AWD_TFSAOIT150044_2036_-NONE-_-NONE-"
    },
    {
        "internal_id": 31978028,
        "Award ID": "TFSAOIT140059",
        "Recipient Name": "SHI INTERNATIONAL CORP",
        "Start Date": "2014-09-24",
        "End Date": "2015-09-23",
        "Award Amount": 5296.5,
        "Description": "JFROG ARTIFCATORY PRO LICENSE SUBSCRIPTION",
        "Award Type": null,
        "generated_internal_id": "CONT_AWD_TFSAOIT140059_2036_-NONE-_-NONE-"
    },
    {
        "internal_id": 9566171,
        "Award ID": "AG7604D140162",
        "Recipient Name": "GLACIER TECHNOLOGIES, LLC",
        "Start Date": "2014-08-01",
        "End Date": "2015-08-03",
        "Award Amount": 89555.22,
        "Description": "THIS TASK ORDER (TO) SERVES TO ISSUE A USDA FOREST SERVICE (FS) CONTRACT NUMBER AG-7604-D-14-0162.   THIS TO IS ISSUED IN ACCORDANCE WITH THE TERMS AND CONDITIONS OF AG-7604-C-10-0001.  THE CONTRACT TYPE IS A TO FOR WORK ENTITLED \"JFROG ARTIFACTORY AND PUPPET SOFTWARE\"    CALL TYPE:  THIS TO IS ESTABLISHED AS FIRM FIXED PRICE.",
        "Award Type": null,
        "generated_internal_id": "CONT_AWD_AG7604D140162_12C2_AG7604C100001_12C2"
    }
]